{
  "collectionName": "components_resumen_resumen_lists",
  "info": {
    "displayName": "resumen_section_list",
    "icon": "align-right",
    "description": ""
  },
  "options": {},
  "attributes": {
    "title": {
      "type": "string",
      "required": true
    },
    "subtitle": {
      "type": "string",
      "unique": false,
      "required": true
    },
    "dates": {
      "type": "string"
    },
    "image": {
      "type": "media",
      "multiple": false,
      "required": false,
      "allowedTypes": [
        "images",
        "files"
      ]
    },
    "detail": {
      "type": "richtext"
    },
    "tags": {
      "type": "relation",
      "relation": "oneToMany",
      "target": "api::tag.tag"
    }
  }
}
